setup.py
hellopyrb/__init__.py
hellopyrb/calc.py
hellopyrb/hello.py
hellopyrb.egg-info/PKG-INFO
hellopyrb.egg-info/SOURCES.txt
hellopyrb.egg-info/dependency_links.txt
hellopyrb.egg-info/top_level.txt